solteron/__init__.py
solteron/solteron.py
solteron-0.1.4.dist-info/LICENSE
solteron-0.1.4.dist-info/METADATA
solteron-0.1.4.dist-info/WHEEL
solteron-0.1.4.dist-info/top_level.txt
solteron-0.1.4.dist-info/RECORD
