Metadata-Version: 2.1
Name: solteron
Version: 0.1.4
Summary: Patrón 'Singleton' en Python 3.
Home-page: https://github.com/Hernanatn/solteron.py
Download-URL: https://pypi.org/project/solteron/0.1.4/#files
Author: Hernán A. Teszkiewicz Novick
Author-email: "Hernán A.T.N." <herni@cajadeideas.ar>
Project-URL: Homepage, https://github.com/Hernanatn/solteron.py
Classifier: Programming Language :: Python :: 3
Classifier: License :: OSI Approved :: MIT License
Classifier: Operating System :: OS Independent
License-File: LICENSE
